LICENSE
ctrader_open_api/__init__.py
ctrader_open_api/auth.py
ctrader_open_api/client.py
ctrader_open_api/endpoints.py
ctrader_open_api/factory.py
ctrader_open_api/messages/OpenApiCommonMessages_pb2.py
ctrader_open_api/messages/OpenApiCommonModelMessages_pb2.py
ctrader_open_api/messages/OpenApiMessages_pb2.py
ctrader_open_api/messages/OpenApiModelMessages_pb2.py
ctrader_open_api/messages/__init__.py
ctrader_open_api/protobuf.py
ctrader_open_api/tcpProtocol.py
ctrader_open_api-0.9.3.dist-info/AUTHORS.md
ctrader_open_api-0.9.3.dist-info/LICENSE
ctrader_open_api-0.9.3.dist-info/METADATA
ctrader_open_api-0.9.3.dist-info/WHEEL
ctrader_open_api-0.9.3.dist-info/RECORD
