Metadata-Version: 2.1
Name: ctrader_open_api
Version: 0.9.3
Summary: A Python package for interacting with cTrader Open API
Home-page: https://github.com/spotware/openApiPy
License: MIT
Author: Spotware
Author-email: connect@spotware.com
Requires-Python: >=3.8,<4.0
Classifier: License :: OSI Approved :: MIT License
Classifier: Natural Language :: English
Classifier: Programming Language :: Python :: 3
Classifier: Programming Language :: Python :: 3.8
Classifier: Programming Language :: Python :: 3.9
Classifier: Programming Language :: Python :: 3.10
Classifier: Programming Language :: Python :: 3.11
Classifier: Programming Language :: Python :: 3.12
Requires-Dist: Twisted (==24.3.0)
Requires-Dist: inputimeout (==1.0.4)
Requires-Dist: protobuf (==3.20.1)
Requires-Dist: pyOpenSSL (==24.1.0)
Requires-Dist: requests (==2.32.3)
Project-URL: Documentation, https://spotware.github.io/OpenApiPy
